{
  "url": "https://steamcommunity.com/profiles/76561198158186950/inventory",
  "tabCounts": {
    "440": 149,
    "570": 12,
    "620": 58,
    "730": 109,
    "753": 482,
    "4920": 1,
    "218620": 63,
    "227300": 25,
    "232090": 367,
    "238460": 7,
    "244930": 16,
    "250820": 4,
    "252490": 7,
    "270880": 3,
    "295110": 3,
    "304930": 25,
    "321360": 1,
    "322330": 4,
    "431240": 1,
    "433850": 75,
    "578080": 59,
    "614910": 2
  },
  "private": false,
  "name": "M4rtiX"
}